DESCRIPTION.rst
MANIFEST.in
README.rst
setup.cfg
setup.py
crowd_pam.egg-info/PKG-INFO
crowd_pam.egg-info/SOURCES.txt
crowd_pam.egg-info/dependency_links.txt
crowd_pam.egg-info/requires.txt
crowd_pam.egg-info/top_level.txt
data/etc/crowd_pam.conf
data/etc/pam.d/common-account
data/etc/pam.d/common-auth
data/etc/pam.d/common-password
data/etc/pam.d/common-session
data/etc/pam.d/common-session-noninteractive
data/man/crowd_pam.8
data/usr/share/pam-configs/pam_config_python
module/__init__.py
module/config.py
module/crowd_auth_utils.py
module/crowd_pam.py
module/error.py
module/getent.py
module/logs.py
scripts/crowd_pam_configure.py