Metadata-Version: 1.1
Name: crowd-pam
Version: 0.0.1
Summary: A PAM module for authenticating with Atlassian Crowd
Home-page: https://bitbucket.org/sam_caldwell/pip-crowd-pam
Author: Sam Caldwell (Atlassian)
Author-email: cst-dev@atlassian.com
License: Apache Software License
Keywords: atlassian crowd sso authentication pam
Platform: UNKNOWN
Classifier: Development Status :: 4 - Beta
Classifier: Intended Audience :: System Administrators
Classifier: Topic :: System :: Systems Administration :: Authentication/Directory
Classifier: License :: OSI Approved :: Apache Software License
Classifier: Programming Language :: Python :: 2.7
